{
  "sections": {
    "main": {
      "type": "single-product",
      "blocks": {
        "heading_wHnFbN": {
          "type": "heading",
          "settings": {}
        },
        "review_WGUCLg": {
          "type": "review",
          "settings": {}
        },
        "short_description_MbcTAW": {
          "type": "short_description",
          "settings": {}
        },
        "variants_kDDC96": {
          "type": "variants",
          "settings": {
            "heading": "2. Purchase Type"
          }
        },
        "price_DpFCTM": {
          "type": "price",
          "settings": {}
        },
        "button_mcjrWg": {
          "type": "button",
          "settings": {
            "button": "ADD TO CART"
          }
        },
        "payment_icon_b98tEr": {
          "type": "payment_icon",
          "settings": {
            "heading": "SECURE & TRUSTED CHECKOUT WITH"
          }
        },
        "speciality_cHqkb4": {
          "type": "speciality",
          "settings": {}
        }
      },
      "block_order": [
        "heading_wHnFbN",
        "review_WGUCLg",
        "short_description_MbcTAW",
        "variants_kDDC96",
        "price_DpFCTM",
        "button_mcjrWg",
        "payment_icon_b98tEr",
        "speciality_cHqkb4"
      ],
      "settings": {
        "color_scheme": "scheme-5dec3c2f-a36d-4067-84c1-c1fae95fc481"
      }
    },
    "related-products": {
      "type": "related-products",
      "settings": {
        "heading": "You may also like",
        "heading_size": "h2",
        "products_to_show": 4,
        "columns_desktop": 4,
        "color_scheme": "scheme-1",
        "image_ratio": "square",
        "image_shape": "default",
        "show_secondary_image": true,
        "show_vendor": false,
        "show_rating": false,
        "columns_mobile": "2",
        "padding_top": 36,
        "padding_bottom": 28
      }
    }
  },
  "order": [
    "main",
    "related-products"
  ]
}
